snsmp2/__init__.py
snsmp2/contextdecorator.py
snsmp2/desbasis.json
snsmp2/desbasis.py
snsmp2/eshlovlp.py
snsmp2/format_output.py
snsmp2/frozencore.py
snsmp2/model.py
snsmp2/optstash.py
snsmp2/resources.py
snsmp2/snsmp2.py
snsmp2/wavefunctioncache.py
snsmp2/weights.npz
snsmp2-1.0.0.dist-info/DESCRIPTION.rst
snsmp2-1.0.0.dist-info/METADATA
snsmp2-1.0.0.dist-info/RECORD
snsmp2-1.0.0.dist-info/WHEEL
snsmp2-1.0.0.dist-info/metadata.json
snsmp2-1.0.0.dist-info/pbr.json
snsmp2-1.0.0.dist-info/top_level.txt
