Metadata-Version: 2.0
Name: snsmp2
Version: 1.0.0
Summary: Spin-network-scaled MP2
Home-page: UNKNOWN
Author: Robert T. McGibbon
Author-email: robert.mcgibbon@deshawresearch.com
License: MIT
Platform: UNKNOWN
Classifier: Development Status :: 4 - Beta
Classifier: Environment :: Console
Classifier: Operating System :: OS Independent
Classifier: Programming Language :: Python
